ksmm/__init__.py
ksmm/__main__.py
ksmm/_version.py
ksmm/handlers.py
ksmm/kernel_schema.py
ksmm/templating.py
ksmm-1.0.0.data/data/etc/jupyter/jupyter_notebook_config.d/ksmm.json
ksmm-1.0.0.data/data/etc/jupyter/jupyter_server_config.d/ksmm.json
ksmm-1.0.0.data/data/share/jupyter/labextensions/@deshaw/jupyterlab-ksmm/package.json
ksmm-1.0.0.data/data/share/jupyter/labextensions/@deshaw/jupyterlab-ksmm/static/242.f60140add870179ad59e.js
ksmm-1.0.0.data/data/share/jupyter/labextensions/@deshaw/jupyterlab-ksmm/static/347.b512b76436999d57a410.js
ksmm-1.0.0.data/data/share/jupyter/labextensions/@deshaw/jupyterlab-ksmm/static/398.d9a69f7a000bc3a9d471.js
ksmm-1.0.0.data/data/share/jupyter/labextensions/@deshaw/jupyterlab-ksmm/static/402.7088997d43120b9a2d08.js
ksmm-1.0.0.data/data/share/jupyter/labextensions/@deshaw/jupyterlab-ksmm/static/402.7088997d43120b9a2d08.js.LICENSE.txt
ksmm-1.0.0.data/data/share/jupyter/labextensions/@deshaw/jupyterlab-ksmm/static/429.269269370741cd78794d.js
ksmm-1.0.0.data/data/share/jupyter/labextensions/@deshaw/jupyterlab-ksmm/static/429.269269370741cd78794d.js.LICENSE.txt
ksmm-1.0.0.data/data/share/jupyter/labextensions/@deshaw/jupyterlab-ksmm/static/486.70a813ef67c6ac9abfcf.js
ksmm-1.0.0.data/data/share/jupyter/labextensions/@deshaw/jupyterlab-ksmm/static/544.b29d5b9b345156c98707.js
ksmm-1.0.0.data/data/share/jupyter/labextensions/@deshaw/jupyterlab-ksmm/static/604.03ea173a4d8f92bba217.js
ksmm-1.0.0.data/data/share/jupyter/labextensions/@deshaw/jupyterlab-ksmm/static/747.7c0d8864089b761844bb.js
ksmm-1.0.0.data/data/share/jupyter/labextensions/@deshaw/jupyterlab-ksmm/static/760.c9a4a1e4fca2d4edc2dd.js
ksmm-1.0.0.data/data/share/jupyter/labextensions/@deshaw/jupyterlab-ksmm/static/760.c9a4a1e4fca2d4edc2dd.js.LICENSE.txt
ksmm-1.0.0.data/data/share/jupyter/labextensions/@deshaw/jupyterlab-ksmm/static/893.2f0d6c56c525319010f1.js
ksmm-1.0.0.data/data/share/jupyter/labextensions/@deshaw/jupyterlab-ksmm/static/893.2f0d6c56c525319010f1.js.LICENSE.txt
ksmm-1.0.0.dist-info/METADATA
ksmm-1.0.0.dist-info/WHEEL
ksmm-1.0.0.dist-info/licenses/LICENSE
ksmm-1.0.0.dist-info/RECORD
