Metadata-Version: 2.1
Name: ksmm
Version: 1.0.0
Summary: An extension to manage Kernelspecs from JupyterLab
Project-URL: Homepage, https://github.com/deshaw/ksmm
Project-URL: Bug Tracker, https://github.com/deshaw/ksmm/issues
Project-URL: Repository, https://github.com/deshaw/ksmm
License: The MIT License (MIT)
License-File: LICENSE
Classifier: Framework :: Jupyter
Classifier: Framework :: Jupyter :: JupyterLab
Classifier: Framework :: Jupyter :: JupyterLab :: 4
Classifier: Framework :: Jupyter :: JupyterLab :: Extensions
Classifier: Framework :: Jupyter :: JupyterLab :: Extensions :: Prebuilt
Classifier: License :: OSI Approved :: BSD License
Classifier: Programming Language :: Python
Classifier: Programming Language :: Python :: 3
Classifier: Programming Language :: Python :: 3.8
Classifier: Programming Language :: Python :: 3.9
Classifier: Programming Language :: Python :: 3.10
Classifier: Programming Language :: Python :: 3.11
Requires-Python: >=3.8
Requires-Dist: jupyter-server<3,>=2.0.1
Provides-Extra: test
Requires-Dist: pytest; extra == 'test'
